Metadata-Version: 1.2
Name: tb-rest-client3
Version: 1.3
Summary: ThingsBoard REST API client
Home-page: https://thingsboard.io/docs/reference/python-rest-client/
Author-email: info@thingsboard.io
License: Apache Software License (Apache Software License 2.0)
Download-URL: https://github.com/thingsboard/python-/archive/1.3.tar.gz
Keywords: IoT,ThingsBoard,ThingsBoard REST API client
Platform: UNKNOWN
Requires-Python: >=3.5
